thinst/__init__.py
thinst/core.py
thinst/plots.py
thinst-0.0.8.dist-info/licenses/LICENSE
thinst-0.0.8.dist-info/METADATA
thinst-0.0.8.dist-info/WHEEL
thinst-0.0.8.dist-info/top_level.txt
thinst-0.0.8.dist-info/RECORD
